djmail/__init__.py
djmail/gmail.py
djmail/templates/email.html
mp_email-0.0.4.dist-info/LICENSE
mp_email-0.0.4.dist-info/METADATA
mp_email-0.0.4.dist-info/WHEEL
mp_email-0.0.4.dist-info/top_level.txt
mp_email-0.0.4.dist-info/RECORD
