Metadata-Version: 2.1
Name: mp-email
Version: 0.0.4
Summary: Django mail app
Home-page: https://github.com/pmaigutyak/djmail
Download-URL: https://github.com/pmaigutyak/djmail/archive/0.0.4.tar.gz
Author: Paul Maigutyak
Author-email: pmaigutyak@gmail.com
License: MIT
License-File: LICENSE
